[
    {
        "@id": "https://shibusawa-dlab.github.io/lab1/api/place/東北地方",
        "@type": [
            "https://jpsearch.go.jp/term/type/Place"
        ],
        "http://schema.org/description": [
            {
                "@language": "ja",
                "@value": "東北地方（とうほくちほう）は、日本の地域のひとつであり、本州東北部に位置している。「奥羽地方（おううちほう）」ともいう。その範囲に法律上の明確な定義はないものの、一般には青森県、岩手県、宮城県、秋田県、山形県、福島県の6県を指す。これら6県は、本州の約3割の面積を占める。東北地方は東日本に位置するが、気象や歴史地理学などでは北海道と一緒に北日本とされる。"
            }
        ],
        "http://schema.org/geo": [
            {
                "@id": "http://geohash.org/xnuj33d2zm86"
            }
        ],
        "http://schema.org/image": [
            {
                "@id": "http://commons.wikimedia.org/wiki/Special:FilePath/Japan_Tohoku_Region_large.png?width=300"
            }
        ],
        "http://www.w3.org/2000/01/rdf-schema#label": [
            {
                "@value": "東北地方"
            }
        ],
        "http://www.w3.org/2002/07/owl#sameAs": [
            {
                "@id": "http://ja.dbpedia.org/resource/東北地方"
            },
            {
                "@id": "http://www.wikidata.org/entity/Q129465"
            },
            {
                "@id": "http://dbpedia.org/resource/Tōhoku_region"
            }
        ]
    }
]