{
    "agential": [
        "皆川"
    ],
    "agential_uri": [
        "https://shibusawa-dlab.github.io/lab1/api/chname/皆川"
    ],
    "canvas": "https://eiichi.shibusawa.or.jp/denkishiryo-bekkan/api/presentations/iiif/1/canvas/406",
    "category": {
        "lvl0": "DKB01 渋沢栄一伝記資料. 別巻第1 日記 (慶応4年-大正3年)",
        "lvl1": "DKB01 渋沢栄一伝記資料. 別巻第1 日記 (慶応4年-大正3年) > DKB10013m 明治三十八年 1905"
    },
    "category_lvl0": "DKB01 渋沢栄一伝記資料. 別巻第1 日記 (慶応4年-大正3年)",
    "category_lvl1": "DKB10013m 明治三十八年 1905",
    "date": {
        "lvl0": "1905",
        "lvl1": "1905 > 1905-08",
        "lvl2": "1905 > 1905-08 > 1905-08-13"
    },
    "date_lvl0": "1905",
    "date_lvl1": "1905-08",
    "date_lvl2": "1905-08-13",
    "description": "\n\n\n        八月十三日\n       \n       日　曇　冷気\n      \n\n\n        午前五時半\n       \n       起床先ツ入浴ス、浴後日記ヲ整理ス、朝飧後新聞紙ヲ一覧シ、諸方ヘノ書状ヲ裁ス、畢テ午前ノ散歩ヲ試ミ千条ケ滝ヲ一覧シ\n       \n        仙元山\n       \n       ノ半腹マテ登臨ス、然レトモ天候悪シキヲ以テ中途ニシテ帰宿ス午後\n       \n\n         皆川\n        \n\n       夫人来ル\n       \n       夕方又散歩、\n       \n        小涌谷\n       \n       ノ源ヲ尋ヌ、水源ハ楼ノ背面ナル山腹ニアリ、登ルコト凡ソ八丁計ナリ、山路草木繁茂シテ行程不便ナリ\n      \n",
    "label": "八月十三日              日　曇　冷気",
    "manifest": "https://eiichi.shibusawa.or.jp/denkishiryo-bekkan/api/presentations/iiif/1/manifest",
    "next": "DKB10013m-0219",
    "objectID": "DKB10013m-0218",
    "prev": "DKB10013m-0217",
    "sort": "DKB10013m-0218",
    "source": "https://shibusawa-dlab.github.io/lab1/tei/DKB01.xml",
    "spatial": [
        "仙元山",
        "小涌谷"
    ],
    "spatial_uri": [
        "https://shibusawa-dlab.github.io/lab1/api/place/仙元山",
        "https://shibusawa-dlab.github.io/lab1/api/place/小涌谷"
    ],
    "temporal": "1905-08-13",
    "texts": [
        "DKB10013m-0169",
        "DKB10017m-0163",
        "DKB10016m-0218",
        "DKB10013m-0207",
        "DKB10013m-0221",
        "DKB10013m-0120",
        "DKB10013m-0176",
        "DKB10013m-0219",
        "DKB10018m-0117",
        "DKB10019m-0327",
        "DKB10016m-0054",
        "DKB10018m-0136",
        "DKB10011m-0367",
        "DKB10018m-0062",
        "DKB10013m-0208",
        "DKB10016m-0222",
        "DKB10013m-0101",
        "DKB10012m-0053",
        "DKB10018m-0248",
        "DKB10013m-0211"
    ],
    "time": {
        "05:30:00": "<div><time when=\"05:30:00\">\n        午前五時半\n       </time>\n       起床先ツ入浴ス、浴後日記ヲ整理ス、朝飧後新聞紙ヲ一覧シ、諸方ヘノ書状ヲ裁ス、畢テ午前ノ散歩ヲ試ミ千条ケ滝ヲ一覧シ\n       <placeName corresp=\"#place_仙元山\">\n        仙元山\n       </placeName>\n       ノ半腹マテ登臨ス、然レトモ天候悪シキヲ以テ中途ニシテ帰宿ス午後\n       <persName corresp=\"#pers_皆川\">\n<surname>\n         皆川\n        </surname>\n</persName>\n       夫人来ル\n       <lb/>\n       夕方又散歩、\n       <placeName corresp=\"#place_小涌谷\">\n        小涌谷\n       </placeName>\n       ノ源ヲ尋ヌ、水源ハ楼ノ背面ナル山腹ニアリ、登ルコト凡ソ八丁計ナリ、山路草木繁茂シテ行程不便ナリ</div>"
    },
    "type": "diary-entry",
    "xml": "<div type=\"diary-entry\" xml:id=\"DKB10013m-0218\">\n<head>\n<date when=\"1905-08-13\">\n        八月十三日\n       </date>\n       日　曇　冷気\n      </head>\n<p>\n<time when=\"05:30:00\">\n        午前五時半\n       </time>\n       起床先ツ入浴ス、浴後日記ヲ整理ス、朝飧後新聞紙ヲ一覧シ、諸方ヘノ書状ヲ裁ス、畢テ午前ノ散歩ヲ試ミ千条ケ滝ヲ一覧シ\n       <placeName corresp=\"#place_仙元山\">\n        仙元山\n       </placeName>\n       ノ半腹マテ登臨ス、然レトモ天候悪シキヲ以テ中途ニシテ帰宿ス午後\n       <persName corresp=\"#pers_皆川\">\n<surname>\n         皆川\n        </surname>\n</persName>\n       夫人来ル\n       <lb/>\n       夕方又散歩、\n       <placeName corresp=\"#place_小涌谷\">\n        小涌谷\n       </placeName>\n       ノ源ヲ尋ヌ、水源ハ楼ノ背面ナル山腹ニアリ、登ルコト凡ソ八丁計ナリ、山路草木繁茂シテ行程不便ナリ\n      </p>\n</div>",
    "year": "1905",
    "yearAndMonth": "1905-08"
}