{
    "agential": [
        "菅原松吉",
        "落合高晁",
        "李元錫",
        "辜鴻銘",
        "白仁武",
        "水島鉄也"
    ],
    "agential_uri": [
        "https://shibusawa-dlab.github.io/lab1/api/chname/菅原松吉",
        "https://shibusawa-dlab.github.io/lab1/api/chname/落合高晁",
        "https://shibusawa-dlab.github.io/lab1/api/chname/李元錫",
        "https://shibusawa-dlab.github.io/lab1/api/chname/辜鴻銘",
        "https://shibusawa-dlab.github.io/lab1/api/chname/白仁武",
        "https://shibusawa-dlab.github.io/lab1/api/chname/水島鉄也"
    ],
    "canvas": "https://eiichi.shibusawa.or.jp/denkishiryo-bekkan/api/presentations/iiif/2/canvas/1481",
    "category": {
        "lvl0": "DKB02 渋沢栄一伝記資料. 別巻第2 日記 (大正4年-昭和5年), 集会日時通知表",
        "lvl1": "DKB02 渋沢栄一伝記資料. 別巻第2 日記 (大正4年-昭和5年), 集会日時通知表 > DKB20026m 大正十三年 1924"
    },
    "category_lvl0": "DKB02 渋沢栄一伝記資料. 別巻第2 日記 (大正4年-昭和5年), 集会日時通知表",
    "category_lvl1": "DKB20026m 大正十三年 1924",
    "date": {
        "lvl0": "1924",
        "lvl1": "1924 > 1924-11",
        "lvl2": "1924 > 1924-11 > 1924-11-11"
    },
    "date_lvl0": "1924",
    "date_lvl1": "1924-11",
    "date_lvl2": "1924-11-11",
    "description": "\n\n\n           十一日\n          \n          （火）\n         \n\n\n\n\n             午前八時\n            \n\n\n              菅原\n             \n\n              松吉\n             \n\n            氏来邸約（\n            \n             アスカ山邸\n            \n            ）\n           \n\n\n\n\n             〃八時半\n            \n\n             千葉県\n            \n            西雲寺\n            \n\n              落合\n             \n\n              高晁\n             \n\n            来邸《（氏脱）》\n           \n\n\n\n\n             午前九時\n            \n\n\n              李\n             \n\n              元錫\n             \n\n            氏来邸約\n            \n             アスカ山邸\n            \n\n\n\n\n\n             午前十時\n            \n\n\n              辜\n             \n\n              鴻銘\n             \n\n            氏ト御会見（\n            \n             アスカ山邸\n            \n            ）\n           \n\n\n\n\n             午後二頃時\n            \n            石橋画伯邸ヘ御出向\n           \n\n\n\n\n             午後三時\n            \n\n\n              白仁\n             \n\n              武\n             \n\n            氏来約（事務所）\n           \n\n\n\n\n             午後三時\n            \n            水鳥鉄也氏来約《（\n            \n\n              水島\n             \n\n              鉄也\n             \n\n            氏）》\n           \n\n\n\n\n             午後正五時\n            \n            平和記念講演会（商工奨励館）\n           \n\n\n",
    "label": "十一日                    （火）",
    "manifest": "https://eiichi.shibusawa.or.jp/denkishiryo-bekkan/api/presentations/iiif/2/manifest",
    "next": "DKB20026m-0312",
    "objectID": "DKB20026m-0311",
    "prev": "DKB20026m-0310",
    "sort": "DKB20026m-0311",
    "source": "https://shibusawa-dlab.github.io/lab1/tei/DKB02.xml",
    "spatial": [
        "飛鳥山邸",
        "千葉県"
    ],
    "spatial_uri": [
        "https://shibusawa-dlab.github.io/lab1/api/place/飛鳥山邸",
        "https://shibusawa-dlab.github.io/lab1/api/place/千葉県"
    ],
    "temporal": "1924-11-11",
    "texts": [
        "DKB20026m-0037",
        "DKB20028m-0037",
        "DKB20027m-0170",
        "DKB20028m-0237",
        "DKB20027m-0047",
        "DKB20029m-0322",
        "DKB20026m-0289",
        "DKB20028m-0246",
        "DKB20029m-0265",
        "DKB20029m-0053",
        "DKB20026m-0280",
        "DKB20028m-0239",
        "DKB20026m-0307",
        "DKB20029m-0331",
        "DKB20027m-0069",
        "DKB20022m-0044",
        "DKB20030m-0193",
        "DKB20027m-0117",
        "DKB20028m-0194",
        "DKB20032m-0136"
    ],
    "time": {
        "08:00:00": "<div><time when=\"08:00:00\">\n             午前八時\n            </time>\n<persName corresp=\"#pers_菅原松吉\">\n<surname>\n              菅原\n             </surname>\n<forename>\n              松吉\n             </forename>\n</persName>\n            氏来邸約（\n            <placeName corresp=\"#place_飛鳥山邸\">\n             アスカ山邸\n            </placeName>\n            ）</div>"
    },
    "type": "day",
    "xml": "<div type=\"day\" xml:id=\"DKB20026m-0311\">\n<head>\n<date when=\"1924-11-11\">\n           十一日\n          </date>\n          （火）\n         </head>\n<listEvent>\n<event>\n<p>\n<time when=\"08:00:00\">\n             午前八時\n            </time>\n<persName corresp=\"#pers_菅原松吉\">\n<surname>\n              菅原\n             </surname>\n<forename>\n              松吉\n             </forename>\n</persName>\n            氏来邸約（\n            <placeName corresp=\"#place_飛鳥山邸\">\n             アスカ山邸\n            </placeName>\n            ）\n           </p>\n</event>\n<event>\n<p>\n<time when=\"08:30:00\">\n             〃八時半\n            </time>\n<placeName corresp=\"#place_千葉県\">\n             千葉県\n            </placeName>\n            西雲寺\n            <persName corresp=\"#pers_落合高晁\">\n<surname>\n              落合\n             </surname>\n<forename>\n              高晁\n             </forename>\n</persName>\n            来邸《（氏脱）》\n           </p>\n</event>\n<event>\n<p>\n<time when=\"09:00:00\">\n             午前九時\n            </time>\n<persName corresp=\"#pers_李元錫\">\n<surname>\n              李\n             </surname>\n<forename>\n              元錫\n             </forename>\n</persName>\n            氏来邸約\n            <placeName corresp=\"#place_飛鳥山邸\">\n             アスカ山邸\n            </placeName>\n</p>\n</event>\n<event>\n<p>\n<time when=\"10:00:00\">\n             午前十時\n            </time>\n<persName corresp=\"#pers_辜鴻銘\">\n<surname>\n              辜\n             </surname>\n<forename>\n              鴻銘\n             </forename>\n</persName>\n            氏ト御会見（\n            <placeName corresp=\"#place_飛鳥山邸\">\n             アスカ山邸\n            </placeName>\n            ）\n           </p>\n</event>\n<event>\n<p>\n<time when=\"14:00:00\">\n             午後二頃時\n            </time>\n            石橋画伯邸ヘ御出向\n           </p>\n</event>\n<event>\n<p>\n<time when=\"15:00:00\">\n             午後三時\n            </time>\n<persName corresp=\"#pers_白仁武\">\n<surname>\n              白仁\n             </surname>\n<forename>\n              武\n             </forename>\n</persName>\n            氏来約（事務所）\n           </p>\n</event>\n<event>\n<p>\n<time when=\"15:00:00\">\n             午後三時\n            </time>\n            水鳥鉄也氏来約《（\n            <persName corresp=\"#pers_水島鉄也\">\n<surname>\n              水島\n             </surname>\n<forename>\n              鉄也\n             </forename>\n</persName>\n            氏）》\n           </p>\n</event>\n<event>\n<p>\n<time when=\"17:00:00\">\n             午後正五時\n            </time>\n            平和記念講演会（商工奨励館）\n           </p>\n</event>\n</listEvent>\n</div>",
    "year": "1924",
    "yearAndMonth": "1924-11"
}