{
    "agential": [
        "北垣国道",
        "松本",
        "黒田",
        "梅浦精一",
        "唐崎恭三",
        "西尾市"
    ],
    "agential_uri": [
        "https://shibusawa-dlab.github.io/lab1/api/chname/北垣国道",
        "https://shibusawa-dlab.github.io/lab1/api/chname/松本",
        "https://shibusawa-dlab.github.io/lab1/api/chname/黒田",
        "https://shibusawa-dlab.github.io/lab1/api/chname/西尾市"
    ],
    "canvas": "https://eiichi.shibusawa.or.jp/denkishiryo-bekkan/api/presentations/iiif/1/canvas/135",
    "category": {
        "lvl0": "DKB01 渋沢栄一伝記資料. 別巻第1 日記 (慶応4年-大正3年)",
        "lvl1": "DKB01 渋沢栄一伝記資料. 別巻第1 日記 (慶応4年-大正3年) > DKB10008m 明治三十二年  1899"
    },
    "category_lvl0": "DKB01 渋沢栄一伝記資料. 別巻第1 日記 (慶応4年-大正3年)",
    "category_lvl1": "DKB10008m 明治三十二年  1899",
    "date": {
        "lvl0": "1899",
        "lvl1": "1899 > 1899-11",
        "lvl2": "1899 > 1899-11 > 1899-11-04"
    },
    "date_lvl0": "1899",
    "date_lvl1": "1899-11",
    "date_lvl2": "1899-11-04",
    "description": "\n\n 十一月四日 \n\n晴、朝北垣国道氏来ル、職制ノ事ヲ談ス、松本某来ル、黒田侯爵ノ名刺持参ニテ東邦協会ノ委員来ル、午後第一銀行ニ出勤ス、梅浦精一氏唐崎恭三氏、台湾鉄道書記西尾等来ル、午後六時浜町ニ帰宿ス\n",
    "fullname": [
        "北垣国道",
        "梅浦精一",
        "唐崎恭三"
    ],
    "label": "十一月四日",
    "manifest": "https://eiichi.shibusawa.or.jp/denkishiryo-bekkan/api/presentations/iiif/1/manifest",
    "next": "DKB10008m-310",
    "objectID": "DKB10008m-309",
    "prev": "DKB10008m-308",
    "sort": "DKB10008m-0309",
    "source": "https://shibusawa-dlab.github.io/lab1/tei/DKB01.xml",
    "spatial": [
        "浜町"
    ],
    "spatial_uri": [
        "https://shibusawa-dlab.github.io/lab1/api/place/浜町"
    ],
    "temporal": "1899-11-04",
    "time": {
        "18:00:00": "<div><pb n=\"B1110\"/><lb/>晴、朝<persName><surname>北垣</surname><forename>国道</forename></persName>氏来ル、職制ノ事ヲ談ス、<persName><surname>松本</surname></persName>某来ル、<persName><surname>黒田</surname></persName>侯爵ノ名刺持参ニテ東邦協会ノ委員来ル、午後<orgName>第一銀行</orgName>ニ出勤ス、<persName><surname>梅浦</surname><forename>精一</forename></persName>氏<persName><surname>唐崎</surname><forename>恭三</forename></persName>氏、台湾鉄道書記<persName><surname>西尾</surname></persName>等来ル、<time when=\"18:00:00\">午後六時</time><placeName>浜町</placeName>ニ帰宿ス</div>"
    },
    "type": "diary-entry",
    "xml": "<div type=\"diary-entry\" xml:id=\"DKB10008m-309\">\n<head>\n<date when=\"1899-11-04\"> 十一月四日 </date>\n</head>\n<p><pb n=\"B1110\"/><lb/>晴、朝<persName><surname>北垣</surname><forename>国道</forename></persName>氏来ル、職制ノ事ヲ談ス、<persName><surname>松本</surname></persName>某来ル、<persName><surname>黒田</surname></persName>侯爵ノ名刺持参ニテ東邦協会ノ委員来ル、午後<orgName>第一銀行</orgName>ニ出勤ス、<persName><surname>梅浦</surname><forename>精一</forename></persName>氏<persName><surname>唐崎</surname><forename>恭三</forename></persName>氏、台湾鉄道書記<persName><surname>西尾</surname></persName>等来ル、<time when=\"18:00:00\">午後六時</time><placeName>浜町</placeName>ニ帰宿ス</p>\n</div>",
    "year": "1899",
    "yearAndMonth": "1899-11"
}