{
    "agential": [
        "本山",
        "鳥尾",
        "松尾"
    ],
    "agential_uri": [
        "https://shibusawa-dlab.github.io/lab1/api/chname/本山",
        "https://shibusawa-dlab.github.io/lab1/api/chname/鳥尾",
        "https://shibusawa-dlab.github.io/lab1/api/chname/松尾"
    ],
    "canvas": "https://eiichi.shibusawa.or.jp/denkishiryo-bekkan/api/presentations/iiif/1/canvas/388",
    "category": {
        "lvl0": "DKB01 渋沢栄一伝記資料. 別巻第1 日記 (慶応4年-大正3年)",
        "lvl1": "DKB01 渋沢栄一伝記資料. 別巻第1 日記 (慶応4年-大正3年) > DKB10013m 明治三十八年 1905"
    },
    "category_lvl0": "DKB01 渋沢栄一伝記資料. 別巻第1 日記 (慶応4年-大正3年)",
    "category_lvl1": "DKB10013m 明治三十八年 1905",
    "date": {
        "lvl0": "1905",
        "lvl1": "1905 > 1905-04",
        "lvl2": "1905 > 1905-04 > 1905-04-18"
    },
    "date_lvl0": "1905",
    "date_lvl1": "1905-04",
    "date_lvl2": "1905-04-18",
    "description": "\n\n\n        四月十八日\n       \n       火　晴　風強シ\n      \n\n\n        午前七時\n       \n       起床、庭園ヲ散歩シ、\n       \n        八時\n       \n       朝飧ヲ畢ル、食後新聞紙ヲ一覧シ\n       \n        十時\n       \n       過\n       \n        小石川\n       \n\n        原町\n       \n       ニ抵リ\n       \n\n         本山\n        \n\n       氏ヲ訪ヒ銅像ノ模型ヲ一覧ス、\n       \n        十一時\n       \n\n        兜町\n       \n       事務所ニ抵リ書状ヲ裁シ来人ニ接ス、\n       \n        十二時\n       \n\n        第一銀行\n       \n       ニ於テ午飧シ\n       \n        一時\n       \n       築地本願寺ニ抵リ\n       \n\n         鳥尾\n        \n\n       氏ノ葬儀ニ列席ス、畢テ再ヒ\n       \n        兜町\n       \n       ニ抵リ\n       \n        韓国\n       \n       其他ヘノ書状ヲ裁シ、来状ヲ点検ス\n       \n       来ル\n       \n        二十日\n       \n\n        午前十一時\n       \n       銀行集会所ニ於テ各銀行会同ノ事ヲ通知セシム\n       \n        午後九時\n       \n       過\n       \n        王子別荘\n       \n       ニ帰宿ス\n       \n\n\n         松尾\n        \n\n       総裁ト電話ニテ国庫債券発行ノ事ヲ談話ス\n      \n",
    "label": "四月十八日              火　晴　風強シ",
    "manifest": "https://eiichi.shibusawa.or.jp/denkishiryo-bekkan/api/presentations/iiif/1/manifest",
    "next": "DKB10013m-0109",
    "objectID": "DKB10013m-0108",
    "prev": "DKB10013m-0107",
    "sort": "DKB10013m-0108",
    "source": "https://shibusawa-dlab.github.io/lab1/tei/DKB01.xml",
    "spatial": [
        "小石川",
        "原町",
        "日本橋兜町",
        "大韓民国",
        "飛鳥山邸"
    ],
    "spatial_uri": [
        "https://shibusawa-dlab.github.io/lab1/api/place/小石川",
        "https://shibusawa-dlab.github.io/lab1/api/place/原町",
        "https://shibusawa-dlab.github.io/lab1/api/place/日本橋兜町",
        "https://shibusawa-dlab.github.io/lab1/api/place/大韓民国",
        "https://shibusawa-dlab.github.io/lab1/api/place/飛鳥山邸"
    ],
    "temporal": "1905-04-18",
    "texts": [
        "DKB10013m-0112",
        "DKB10013m-0135",
        "DKB10013m-0123",
        "DKB10013m-0153",
        "DKB10013m-0210",
        "DKB10016m-0116",
        "DKB10013m-0310",
        "DKB10013m-0250",
        "DKB10013m-0056",
        "DKB10013m-0143",
        "DKB10013m-0322",
        "DKB10014m-0012",
        "DKB10013m-0191",
        "DKB10013m-0303",
        "DKB10013m-0152",
        "DKB10014m-0094",
        "DKB10013m-0132",
        "DKB10013m-0313",
        "DKB10013m-0096",
        "DKB10013m-0119"
    ],
    "time": {
        "07:00:00": "<div><time when=\"07:00:00\">\n        午前七時\n       </time>\n       起床、庭園ヲ散歩シ、</div>",
        "08:00:00": "<div><time when=\"08:00:00\">\n        八時\n       </time>\n       朝飧ヲ畢ル、食後新聞紙ヲ一覧シ</div>",
        "10:00:00": "<div><time when=\"10:00:00\">\n        十時\n       </time>\n       過\n       <placeName corresp=\"#place_小石川\">\n        小石川\n       </placeName>\n<placeName corresp=\"#place_原町\">\n        原町\n       </placeName>\n       ニ抵リ\n       <persName corresp=\"#pers_本山\">\n<surname>\n         本山\n        </surname>\n</persName>\n       氏ヲ訪ヒ銅像ノ模型ヲ一覧ス、</div>",
        "11:00:00": "<div><time when=\"11:00:00\">\n        午前十一時\n       </time>\n       銀行集会所ニ於テ各銀行会同ノ事ヲ通知セシム</div>",
        "12:00:00": "<div><time when=\"12:00:00\">\n        十二時\n       </time>\n<orgName>\n        第一銀行\n       </orgName>\n       ニ於テ午飧シ</div>",
        "13:00:00": "<div><time when=\"13:00:00\">\n        一時\n       </time>\n       築地本願寺ニ抵リ\n       <persName corresp=\"#pers_鳥尾\">\n<surname>\n         鳥尾\n        </surname>\n</persName>\n       氏ノ葬儀ニ列席ス、畢テ再ヒ\n       <placeName corresp=\"#place_日本橋兜町\">\n        兜町\n       </placeName>\n       ニ抵リ\n       <placeName corresp=\"#place_大韓民国\">\n        韓国\n       </placeName>\n       其他ヘノ書状ヲ裁シ、来状ヲ点検ス\n       <lb/>\n       来ル\n       <date evidence=\"year inferenced, month\" when=\"1905-04-20\">\n        二十日\n       </date></div>",
        "21:00:00": "<div><time when=\"21:00:00\">\n        午後九時\n       </time>\n       過\n       <placeName corresp=\"#place_飛鳥山邸\">\n        王子別荘\n       </placeName>\n       ニ帰宿ス\n       <lb/>\n<persName corresp=\"#pers_松尾\">\n<surname>\n         松尾\n        </surname>\n</persName>\n       総裁ト電話ニテ国庫債券発行ノ事ヲ談話ス</div>"
    },
    "type": "diary-entry",
    "xml": "<div type=\"diary-entry\" xml:id=\"DKB10013m-0108\">\n<head>\n<date when=\"1905-04-18\">\n        四月十八日\n       </date>\n       火　晴　風強シ\n      </head>\n<p>\n<time when=\"07:00:00\">\n        午前七時\n       </time>\n       起床、庭園ヲ散歩シ、\n       <time when=\"08:00:00\">\n        八時\n       </time>\n       朝飧ヲ畢ル、食後新聞紙ヲ一覧シ\n       <time when=\"10:00:00\">\n        十時\n       </time>\n       過\n       <placeName corresp=\"#place_小石川\">\n        小石川\n       </placeName>\n<placeName corresp=\"#place_原町\">\n        原町\n       </placeName>\n       ニ抵リ\n       <persName corresp=\"#pers_本山\">\n<surname>\n         本山\n        </surname>\n</persName>\n       氏ヲ訪ヒ銅像ノ模型ヲ一覧ス、\n       <time when=\"11:00:00\">\n        十一時\n       </time>\n<placeName corresp=\"#place_日本橋兜町\">\n        兜町\n       </placeName>\n       事務所ニ抵リ書状ヲ裁シ来人ニ接ス、\n       <time when=\"12:00:00\">\n        十二時\n       </time>\n<orgName>\n        第一銀行\n       </orgName>\n       ニ於テ午飧シ\n       <time when=\"13:00:00\">\n        一時\n       </time>\n       築地本願寺ニ抵リ\n       <persName corresp=\"#pers_鳥尾\">\n<surname>\n         鳥尾\n        </surname>\n</persName>\n       氏ノ葬儀ニ列席ス、畢テ再ヒ\n       <placeName corresp=\"#place_日本橋兜町\">\n        兜町\n       </placeName>\n       ニ抵リ\n       <placeName corresp=\"#place_大韓民国\">\n        韓国\n       </placeName>\n       其他ヘノ書状ヲ裁シ、来状ヲ点検ス\n       <lb/>\n       来ル\n       <date evidence=\"year inferenced, month\" when=\"1905-04-20\">\n        二十日\n       </date>\n<time when=\"11:00:00\">\n        午前十一時\n       </time>\n       銀行集会所ニ於テ各銀行会同ノ事ヲ通知セシム\n       <time when=\"21:00:00\">\n        午後九時\n       </time>\n       過\n       <placeName corresp=\"#place_飛鳥山邸\">\n        王子別荘\n       </placeName>\n       ニ帰宿ス\n       <lb/>\n<persName corresp=\"#pers_松尾\">\n<surname>\n         松尾\n        </surname>\n</persName>\n       総裁ト電話ニテ国庫債券発行ノ事ヲ談話ス\n      </p>\n</div>",
    "year": "1905",
    "yearAndMonth": "1905-04"
}