{
    "agential": [
        "中村",
        "大倉",
        "豊川",
        "佐々木",
        "林訒",
        "武之助",
        "押川",
        "織田"
    ],
    "agential_uri": [
        "https://shibusawa-dlab.github.io/lab1/api/chname/中村",
        "https://shibusawa-dlab.github.io/lab1/api/chname/大倉",
        "https://shibusawa-dlab.github.io/lab1/api/chname/豊川",
        "https://shibusawa-dlab.github.io/lab1/api/chname/佐々木",
        "https://shibusawa-dlab.github.io/lab1/api/chname/織田"
    ],
    "canvas": "https://eiichi.shibusawa.or.jp/denkishiryo-bekkan/api/presentations/iiif/1/canvas/655",
    "category": {
        "lvl0": "DKB01 渋沢栄一伝記資料. 別巻第1 日記 (慶応4年-大正3年)",
        "lvl1": "DKB01 渋沢栄一伝記資料. 別巻第1 日記 (慶応4年-大正3年) > DKB10018m 明治四十三年  1910"
    },
    "category_lvl0": "DKB01 渋沢栄一伝記資料. 別巻第1 日記 (慶応4年-大正3年)",
    "category_lvl1": "DKB10018m 明治四十三年  1910",
    "date": {
        "lvl0": "1910",
        "lvl1": "1910 > 1910-06",
        "lvl2": "1910 > 1910-06 > 1910-06-18"
    },
    "date_lvl0": "1910",
    "date_lvl1": "1910-06",
    "date_lvl2": "1910-06-18",
    "description": "\n\n 六月十八日  土　曇　冷 \n午前七時半起床、入浴シ、畢テ朝飧ヲ食シ、後、報知新聞社員中村氏ノ来訪ニ接シ種々ノ談話アリ、十時兜町事務所ニ抵リ、事務ヲ処理シ又来人ニ接ス、十二時銀行倶楽部ニ抵リ、大倉、豊川、佐々木氏等ト東洋汽船会社ノ役員撰挙ノ事ヲ談話ス、畢テ再ヒ事務所ニ於テ事務ヲ処理ス、午後四時日本倶楽部ニ抵リ、委員会ヲ開キ要務ヲ協議ス、六時本郷ニ抵リテ夜飧ス、九時王子ニ帰宿ス、林訒氏来リ、武之助学業ノ事ヲ談話ス此日、午前十時農商務省ニ抵リ二十日ニ開カルヘキ生産調査会ノ事ニ付、押川次官、織田事務官ト種々ノ協議ヲ為ス\n",
    "fullname": [],
    "label": "六月十八日  土　曇　冷",
    "manifest": "https://eiichi.shibusawa.or.jp/denkishiryo-bekkan/api/presentations/iiif/1/manifest",
    "next": "DKB10018m-143",
    "objectID": "DKB10018m-142",
    "prev": "DKB10018m-141",
    "sort": "DKB10018m-0142",
    "source": "https://shibusawa-dlab.github.io/lab1/tei/DKB01.xml",
    "spatial": [
        "日本橋兜町",
        "日本",
        "本郷",
        "王子"
    ],
    "spatial_uri": [
        "https://shibusawa-dlab.github.io/lab1/api/place/日本橋兜町",
        "https://shibusawa-dlab.github.io/lab1/api/place/日本",
        "https://shibusawa-dlab.github.io/lab1/api/place/本郷",
        "https://shibusawa-dlab.github.io/lab1/api/place/王子"
    ],
    "temporal": "1910-06-18",
    "time": {
        "07:30:00": "<div><time when=\"07:30:00\">午前七時半</time>起床、入浴シ、畢テ朝飧ヲ食シ、後、<orgName>報知新聞</orgName>社員<persName><surname>中村</surname></persName>氏ノ来訪ニ接シ種々ノ談話アリ、</div>",
        "10:00:00": "<div><time when=\"10:00:00\">午前十時</time>農商務省ニ抵リ<date evidence=\"year inferenced, month\" when=\"1910-06-20\">二十日</date>ニ開カルヘキ生産調査会ノ事ニ付、<persName><surname>押川</surname></persName>次官、<persName><surname>織田</surname></persName>事務官ト種々ノ協議ヲ為ス</div>",
        "12:00:00": "<div><time when=\"12:00:00\">十二時</time><orgName>銀行倶楽部</orgName>ニ抵リ、<persName><surname>大倉</surname></persName>、<persName><surname>豊川</surname></persName>、<persName><surname>佐々木</surname></persName>氏等ト東洋汽船会社ノ役員撰挙ノ事ヲ談話ス、畢テ再ヒ事務所ニ於テ事務ヲ処理ス、</div>",
        "16:00:00": "<div><time when=\"16:00:00\">午後四時</time><placeName>日本</placeName>倶楽部ニ抵リ、委員会ヲ開キ要務ヲ協議ス、</div>",
        "18:00:00": "<div><time when=\"18:00:00\">六時</time><placeName>本郷</placeName>ニ抵リテ夜飧ス、</div>",
        "21:00:00": "<div><time when=\"21:00:00\">九時</time><placeName>王子</placeName>ニ帰宿ス、<persName>林訒</persName>氏来リ、<persName><forename>武之助</forename></persName>学業ノ事ヲ談話ス<lb/>此日、</div>"
    },
    "type": "diary-entry",
    "xml": "<div type=\"diary-entry\" xml:id=\"DKB10018m-142\">\n<head>\n<date when=\"1910-06-18\"> 六月十八日 </date> 土　曇　冷 </head>\n<p><time when=\"07:30:00\">午前七時半</time>起床、入浴シ、畢テ朝飧ヲ食シ、後、<orgName>報知新聞</orgName>社員<persName><surname>中村</surname></persName>氏ノ来訪ニ接シ種々ノ談話アリ、<time when=\"10:00:00\">十時</time><placeName>兜町</placeName>事務所ニ抵リ、事務ヲ処理シ又来人ニ接ス、<time when=\"12:00:00\">十二時</time><orgName>銀行倶楽部</orgName>ニ抵リ、<persName><surname>大倉</surname></persName>、<persName><surname>豊川</surname></persName>、<persName><surname>佐々木</surname></persName>氏等ト東洋汽船会社ノ役員撰挙ノ事ヲ談話ス、畢テ再ヒ事務所ニ於テ事務ヲ処理ス、<time when=\"16:00:00\">午後四時</time><placeName>日本</placeName>倶楽部ニ抵リ、委員会ヲ開キ要務ヲ協議ス、<time when=\"18:00:00\">六時</time><placeName>本郷</placeName>ニ抵リテ夜飧ス、<time when=\"21:00:00\">九時</time><placeName>王子</placeName>ニ帰宿ス、<persName>林訒</persName>氏来リ、<persName><forename>武之助</forename></persName>学業ノ事ヲ談話ス<lb/>此日、<time when=\"10:00:00\">午前十時</time>農商務省ニ抵リ<date evidence=\"year inferenced, month\" when=\"1910-06-20\">二十日</date>ニ開カルヘキ生産調査会ノ事ニ付、<persName><surname>押川</surname></persName>次官、<persName><surname>織田</surname></persName>事務官ト種々ノ協議ヲ為ス</p>\n</div>",
    "year": "1910",
    "yearAndMonth": "1910-06"
}