{
    "agential": [
        "森村",
        "原六郎",
        "敦子",
        "桂"
    ],
    "agential_uri": [
        "https://shibusawa-dlab.github.io/lab1/api/chname/森村",
        "https://shibusawa-dlab.github.io/lab1/api/chname/原六郎",
        "https://shibusawa-dlab.github.io/lab1/api/chname/桂"
    ],
    "canvas": "https://eiichi.shibusawa.or.jp/denkishiryo-bekkan/api/presentations/iiif/1/canvas/752",
    "category": {
        "lvl0": "DKB01 渋沢栄一伝記資料. 別巻第1 日記 (慶応4年-大正3年)",
        "lvl1": "DKB01 渋沢栄一伝記資料. 別巻第1 日記 (慶応4年-大正3年) > DKB10020m 明治四十五年  1912"
    },
    "category_lvl0": "DKB01 渋沢栄一伝記資料. 別巻第1 日記 (慶応4年-大正3年)",
    "category_lvl1": "DKB10020m 明治四十五年  1912",
    "date": {
        "lvl0": "1912",
        "lvl1": "1912 > 1912-02",
        "lvl2": "1912 > 1912-02 > 1912-02-29"
    },
    "date_lvl0": "1912",
    "date_lvl1": "1912-02",
    "date_lvl2": "1912-02-29",
    "description": "\n\n 二月二十九日  木　曇　軽寒 \n午前七時起床、半身浴ヲナシテ朝飧ヲ食ス、二三ノ電話ヲ通シテ後、日記ヲ編成ス、川越喜多院住職来訪ス、星岳保勝会寄附金ニ関シ不取締ノ行為アリシニ付種々ノ談話ヲ為シテ之ヲ矯正スル事ヲ告ク、午前十時高輪ニ森村氏ヲ訪問シ、又、原六郎氏ノ病ヲ見舞ヒ、十二時過敦子ノ僑居ニ抵リテ午飧ス、帰途三田ニ桂公爵ヲ訪ヒ、午後三時第一銀行ニ抵リ重役会ヲ開ク、要件ヲ議決ス、畢テ事務所ニ抵リテ書類ヲ整理ス、又、来人ト談話ス、夜六時半帰宿シ、夜飧後、新聞紙ヲ読ミ又雑誌ヲ一覧ス\n",
    "fullname": [
        "原六郎"
    ],
    "label": "二月二十九日  木　曇　軽寒",
    "manifest": "https://eiichi.shibusawa.or.jp/denkishiryo-bekkan/api/presentations/iiif/1/manifest",
    "next": "DKB10020m-49",
    "objectID": "DKB10020m-48",
    "prev": "DKB10020m-47",
    "sort": "DKB10020m-0048",
    "source": "https://shibusawa-dlab.github.io/lab1/tei/DKB01.xml",
    "spatial": [
        "川越",
        "高輪",
        "三田"
    ],
    "spatial_uri": [
        "https://shibusawa-dlab.github.io/lab1/api/place/川越",
        "https://shibusawa-dlab.github.io/lab1/api/place/高輪",
        "https://shibusawa-dlab.github.io/lab1/api/place/三田"
    ],
    "temporal": "1912-02-29",
    "time": {
        "07:00:00": "<div><time when=\"07:00:00\">午前七時</time>起床、半身浴ヲナシテ朝飧ヲ食ス、二三ノ電話ヲ通シテ後、日記ヲ編成ス、<placeName>川越</placeName>喜多院住職来訪ス、星岳保勝会寄附金ニ関シ不取締ノ行為アリシニ付種々ノ談話ヲ為シテ之ヲ矯正スル事ヲ告ク、</div>",
        "10:00:00": "<div><time when=\"10:00:00\">午前十時</time><placeName>高輪</placeName>ニ<persName><surname>森村</surname></persName>氏ヲ訪問シ、又、<persName><surname>原</surname><forename>六郎</forename></persName>氏ノ病ヲ見舞ヒ、</div>",
        "12:00:00": "<div><time when=\"12:00:00\">十二時</time>過<persName><forename>敦子</forename></persName>ノ僑居ニ抵リテ午飧ス、帰途<placeName>三田</placeName>ニ<persName><surname>桂</surname></persName>公爵ヲ訪ヒ、</div>",
        "15:00:00": "<div><time when=\"15:00:00\">午後三時</time><orgName>第一銀行</orgName>ニ抵リ重役会ヲ開ク、要件ヲ議決ス、畢テ事務所ニ抵リテ書類ヲ整理ス、又、来人ト談話ス、夜</div>",
        "18:30:00": "<div><time when=\"18:30:00\">六時半</time>帰宿シ、夜飧後、新聞紙ヲ読ミ又雑誌ヲ一覧ス</div>"
    },
    "type": "diary-entry",
    "xml": "<div type=\"diary-entry\" xml:id=\"DKB10020m-48\">\n<head>\n<date when=\"1912-02-29\"> 二月二十九日 </date> 木　曇　軽寒 </head>\n<p><time when=\"07:00:00\">午前七時</time>起床、半身浴ヲナシテ朝飧ヲ食ス、二三ノ電話ヲ通シテ後、日記ヲ編成ス、<placeName>川越</placeName>喜多院住職来訪ス、星岳保勝会寄附金ニ関シ不取締ノ行為アリシニ付種々ノ談話ヲ為シテ之ヲ矯正スル事ヲ告ク、<time when=\"10:00:00\">午前十時</time><placeName>高輪</placeName>ニ<persName><surname>森村</surname></persName>氏ヲ訪問シ、又、<persName><surname>原</surname><forename>六郎</forename></persName>氏ノ病ヲ見舞ヒ、<time when=\"12:00:00\">十二時</time>過<persName><forename>敦子</forename></persName>ノ僑居ニ抵リテ午飧ス、帰途<placeName>三田</placeName>ニ<persName><surname>桂</surname></persName>公爵ヲ訪ヒ、<time when=\"15:00:00\">午後三時</time><orgName>第一銀行</orgName>ニ抵リ重役会ヲ開ク、要件ヲ議決ス、畢テ事務所ニ抵リテ書類ヲ整理ス、又、来人ト談話ス、夜<time when=\"18:30:00\">六時半</time>帰宿シ、夜飧後、新聞紙ヲ読ミ又雑誌ヲ一覧ス</p>\n</div>",
    "year": "1912",
    "yearAndMonth": "1912-02"
}