{
    "agential": [
        "三島",
        "徳川"
    ],
    "agential_uri": [
        "https://shibusawa-dlab.github.io/lab1/api/chname/三島",
        "https://shibusawa-dlab.github.io/lab1/api/chname/徳川"
    ],
    "canvas": "https://eiichi.shibusawa.or.jp/denkishiryo-bekkan/api/presentations/iiif/2/canvas/1202",
    "category": {
        "lvl0": "DKB02 渋沢栄一伝記資料. 別巻第2 日記 (大正4年-昭和5年), 集会日時通知表",
        "lvl1": "DKB02 渋沢栄一伝記資料. 別巻第2 日記 (大正4年-昭和5年), 集会日時通知表 > DKB20018m 大正五年 1916"
    },
    "category_lvl0": "DKB02 渋沢栄一伝記資料. 別巻第2 日記 (大正4年-昭和5年), 集会日時通知表",
    "category_lvl1": "DKB20018m 大正五年 1916",
    "date": {
        "lvl0": "1916",
        "lvl1": "1916 > 1916-05",
        "lvl2": "1916 > 1916-05 > 1916-05-03"
    },
    "date_lvl0": "1916",
    "date_lvl1": "1916-05",
    "date_lvl2": "1916-05-03",
    "description": "\n\n\n           三日\n          \n          （水）\n         \n\n\n\n\n             午後一時\n            \n\n\n              三島\n             \n\n            子爵ヲ御訪問（\n            \n             日本銀行\n            \n            ）\n           \n\n\n\n\n             午後二時\n            \n\n\n              徳川\n             \n\n            貴族院議長ヲ御訪問（華族会館）\n           \n\n\n\n\n             午後五時\n            \n            中央慈善協会ノ件（中央亭）\n           \n\n\n",
    "label": "三日                    （水）",
    "manifest": "https://eiichi.shibusawa.or.jp/denkishiryo-bekkan/api/presentations/iiif/2/manifest",
    "next": "DKB20018m-0106",
    "objectID": "DKB20018m-0105",
    "prev": "DKB20018m-0104",
    "sort": "DKB20018m-0105",
    "source": "https://shibusawa-dlab.github.io/lab1/tei/DKB02.xml",
    "spatial": [],
    "spatial_uri": [],
    "temporal": "1916-05-03",
    "texts": [
        "DKB20018m-0244",
        "DKB20020m-0298",
        "DKB20022m-0032",
        "DKB20018m-0259",
        "DKB20022m-0063",
        "DKB20016m-0043",
        "DKB20018m-0048",
        "DKB20019m-0022",
        "DKB20019m-0335",
        "DKB20023m-0264",
        "DKB20029m-0219",
        "DKB20017m-0139",
        "DKB20019m-0196",
        "DKB20025m-0152",
        "DKB20025m-0273",
        "DKB20020m-0228",
        "DKB20018m-0118",
        "DKB20023m-0059",
        "DKB20021m-0247",
        "DKB20023m-0195"
    ],
    "time": {
        "13:00:00": "<div><time when=\"13:00:00\">\n             午後一時\n            </time>\n<persName corresp=\"#pers_三島\">\n<surname>\n              三島\n             </surname>\n</persName>\n            子爵ヲ御訪問（\n            <orgName>\n             日本銀行\n            </orgName>\n            ）</div>"
    },
    "type": "day",
    "xml": "<div type=\"day\" xml:id=\"DKB20018m-0105\">\n<head>\n<date when=\"1916-05-03\">\n           三日\n          </date>\n          （水）\n         </head>\n<listEvent>\n<event>\n<p>\n<time when=\"13:00:00\">\n             午後一時\n            </time>\n<persName corresp=\"#pers_三島\">\n<surname>\n              三島\n             </surname>\n</persName>\n            子爵ヲ御訪問（\n            <orgName>\n             日本銀行\n            </orgName>\n            ）\n           </p>\n</event>\n<event>\n<p>\n<time when=\"14:00:00\">\n             午後二時\n            </time>\n<persName corresp=\"#pers_徳川\">\n<surname>\n              徳川\n             </surname>\n</persName>\n            貴族院議長ヲ御訪問（華族会館）\n           </p>\n</event>\n<event>\n<p>\n<time when=\"17:00:00\">\n             午後五時\n            </time>\n            中央慈善協会ノ件（中央亭）\n           </p>\n</event>\n</listEvent>\n</div>",
    "year": "1916",
    "yearAndMonth": "1916-05"
}