{
    "agential": [
        "原敬",
        "近藤"
    ],
    "agential_uri": [
        "https://shibusawa-dlab.github.io/lab1/api/chname/原敬",
        "https://shibusawa-dlab.github.io/lab1/api/chname/近藤"
    ],
    "canvas": "https://eiichi.shibusawa.or.jp/denkishiryo-bekkan/api/presentations/iiif/2/canvas/1225",
    "category": {
        "lvl0": "DKB02 渋沢栄一伝記資料. 別巻第2 日記 (大正4年-昭和5年), 集会日時通知表",
        "lvl1": "DKB02 渋沢栄一伝記資料. 別巻第2 日記 (大正4年-昭和5年), 集会日時通知表 > DKB20019m 大正六年 1917"
    },
    "category_lvl0": "DKB02 渋沢栄一伝記資料. 別巻第2 日記 (大正4年-昭和5年), 集会日時通知表",
    "category_lvl1": "DKB20019m 大正六年 1917",
    "date": {
        "lvl0": "1917",
        "lvl1": "1917 > 1917-01",
        "lvl2": "1917 > 1917-01 > 1917-01-18"
    },
    "date_lvl0": "1917",
    "date_lvl1": "1917-01",
    "date_lvl2": "1917-01-18",
    "description": "\n\n 十八日  （木） \n\n\n午後一―午後二時宮内省皇々后職《（后宮）》ヘ御出向ノ約\n\n\n午時　　　　　教育調査会（帝大改正案等調査特別委員会）\n\n\n午後二少々過　原敬氏ヲ御訪問ノ約（同氏邸）近藤男トモニ\n\n\n午後六時大日本人造肥料会社ヨリ御案内（トキワヤ）\n\n\n",
    "fullname": [
        "原敬"
    ],
    "label": "十八日  （木）",
    "manifest": "https://eiichi.shibusawa.or.jp/denkishiryo-bekkan/api/presentations/iiif/2/manifest",
    "next": "DKB20019m-19",
    "objectID": "DKB20019m-18",
    "prev": "DKB20019m-17",
    "sort": "DKB20019m-0018",
    "source": "https://shibusawa-dlab.github.io/lab1/tei/DKB02.xml",
    "spatial": [
        "日本"
    ],
    "spatial_uri": [
        "https://shibusawa-dlab.github.io/lab1/api/place/日本"
    ],
    "temporal": "1917-01-18",
    "time": {},
    "type": "day",
    "xml": "<div type=\"day\" xml:id=\"DKB20019m-18\">\n<head>\n<date when=\"1917-01-18\"> 十八日 </date> （木） </head>\n<listEvent>\n<event>\n<p><time from=\"13:00:00\" to=\"14:00:00\">午後一―午後二時</time>宮内省皇々后職《（后宮）》ヘ御出向ノ約</p>\n</event>\n<event>\n<p><time when=\"12:00:00\">午時</time>　　　　　教育調査会（帝大改正案等調査特別委員会）</p>\n</event>\n<event>\n<p><time when=\"14:00:00\">午後二少々過</time>　<persName><surname>原</surname><forename>敬</forename></persName>氏ヲ御訪問ノ約（同氏邸）<persName><surname>近藤</surname></persName>男トモニ</p>\n</event>\n<event>\n<p><time when=\"18:00:00\">午後六時</time>大<placeName>日本</placeName>人造肥料会社ヨリ御案内（トキワヤ）</p>\n</event>\n</listEvent>\n</div>",
    "year": "1917",
    "yearAndMonth": "1917-01"
}