{
    "agential": [],
    "agential_uri": [],
    "canvas": "https://eiichi.shibusawa.or.jp/denkishiryo-bekkan/api/presentations/iiif/2/canvas/1347",
    "category": {
        "lvl0": "DKB02 渋沢栄一伝記資料. 別巻第2 日記 (大正4年-昭和5年), 集会日時通知表",
        "lvl1": "DKB02 渋沢栄一伝記資料. 別巻第2 日記 (大正4年-昭和5年), 集会日時通知表 > DKB20022m 大正九年 1920"
    },
    "category_lvl0": "DKB02 渋沢栄一伝記資料. 別巻第2 日記 (大正4年-昭和5年), 集会日時通知表",
    "category_lvl1": "DKB20022m 大正九年 1920",
    "date": {
        "lvl0": "1920",
        "lvl1": "1920 > 1920-11",
        "lvl2": "1920 > 1920-11 > 1920-11-21"
    },
    "date_lvl0": "1920",
    "date_lvl1": "1920-11",
    "date_lvl2": "1920-11-21",
    "description": "\n ○二十一日記入ナシ。\n                                                  \n",
    "fullname": [],
    "label": "○二十一日記入ナシ。",
    "manifest": "https://eiichi.shibusawa.or.jp/denkishiryo-bekkan/api/presentations/iiif/2/manifest",
    "next": "DKB20022m-316",
    "objectID": "DKB20022m-304",
    "prev": "DKB20022m-218",
    "sort": "DKB20022m-0304",
    "source": "https://shibusawa-dlab.github.io/lab1/tei/DKB02.xml",
    "spatial": [],
    "spatial_uri": [],
    "temporal": "1920-11-21",
    "time": {},
    "type": "note",
    "xml": "<div type=\"note\" xml:id=\"DKB20022m-304\">\n<head> ○<date when=\"1920-11-21\">二十一日</date>記入ナシ。\n                                                  </head>\n</div>",
    "year": "1920",
    "yearAndMonth": "1920-11"
}