{
    "agential": [
        "神田乃武",
        "高根義人",
        "関直彦",
        "埴原"
    ],
    "agential_uri": [
        "https://shibusawa-dlab.github.io/lab1/api/chname/神田乃武",
        "https://shibusawa-dlab.github.io/lab1/api/chname/高根義人",
        "https://shibusawa-dlab.github.io/lab1/api/chname/関直彦"
    ],
    "canvas": "https://eiichi.shibusawa.or.jp/denkishiryo-bekkan/api/presentations/iiif/2/canvas/1356",
    "category": {
        "lvl0": "DKB02 渋沢栄一伝記資料. 別巻第2 日記 (大正4年-昭和5年), 集会日時通知表",
        "lvl1": "DKB02 渋沢栄一伝記資料. 別巻第2 日記 (大正4年-昭和5年), 集会日時通知表 > DKB20023m 大正十年　1921"
    },
    "category_lvl0": "DKB02 渋沢栄一伝記資料. 別巻第2 日記 (大正4年-昭和5年), 集会日時通知表",
    "category_lvl1": "DKB20023m 大正十年　1921",
    "date": {
        "lvl0": "1921",
        "lvl1": "1921 > 1921-03",
        "lvl2": "1921 > 1921-03 > 1921-03-19"
    },
    "date_lvl0": "1921",
    "date_lvl1": "1921-03",
    "date_lvl2": "1921-03-19",
    "description": "\n\n 十九日  （土） \n\n\n正午　　　　　神田乃武男送別会（飛鳥山邸）\n\n\n午後三半時　　高根義人氏来約（兜町）\n\n\n午後四時関直彦氏来約（兜町）\n\n\n午後四時埼玉学生誘掖会理事会（兜町）\n\n\n午後五時埴原外務次官ヲ御訪問（外務省）\n\n\n",
    "fullname": [
        "神田乃武",
        "高根義人",
        "関直彦"
    ],
    "label": "十九日  （土）",
    "manifest": "https://eiichi.shibusawa.or.jp/denkishiryo-bekkan/api/presentations/iiif/2/manifest",
    "next": "DKB20023m-71",
    "objectID": "DKB20023m-70",
    "prev": "DKB20023m-69",
    "sort": "DKB20023m-0070",
    "source": "https://shibusawa-dlab.github.io/lab1/tei/DKB02.xml",
    "spatial": [
        "飛鳥山邸",
        "日本橋兜町",
        "埼玉"
    ],
    "spatial_uri": [
        "https://shibusawa-dlab.github.io/lab1/api/place/日本橋兜町",
        "https://shibusawa-dlab.github.io/lab1/api/place/埼玉"
    ],
    "temporal": "1921-03-19",
    "time": {
        "12:00:00": "<div><time when=\"12:00:00\">正午</time>　　　　　<persName><surname>神田</surname><forename>乃武</forename></persName>男送別会（<placeName corresp=\"#飛鳥山邸\">飛鳥山邸</placeName>）</div>"
    },
    "type": "day",
    "xml": "<div type=\"day\" xml:id=\"DKB20023m-70\">\n<head>\n<date when=\"1921-03-19\"> 十九日 </date> （土） </head>\n<listEvent>\n<event>\n<p><time when=\"12:00:00\">正午</time>　　　　　<persName><surname>神田</surname><forename>乃武</forename></persName>男送別会（<placeName corresp=\"#飛鳥山邸\">飛鳥山邸</placeName>）</p>\n</event>\n<event>\n<p><time when=\"15:30:00\">午後三半時</time>　　<persName><surname>高根</surname><forename>義人</forename></persName>氏来約（<placeName>兜町</placeName>）</p>\n</event>\n<event>\n<p><time when=\"16:00:00\">午後四時</time><persName><surname>関</surname><forename>直彦</forename></persName>氏来約（<placeName>兜町</placeName>）</p>\n</event>\n<event>\n<p><time when=\"16:00:00\">午後四時</time><placeName>埼玉</placeName>学生誘掖会理事会（<placeName>兜町</placeName>）</p>\n</event>\n<event>\n<p><time when=\"17:00:00\">午後五時</time><persName><surname>埴原</surname></persName>外務次官ヲ御訪問（外務省）</p>\n</event>\n</listEvent>\n</div>",
    "year": "1921",
    "yearAndMonth": "1921-03"
}