{
    "agential": [
        "安藤義喬",
        "安東義喬",
        "入沢"
    ],
    "agential_uri": [],
    "canvas": "https://eiichi.shibusawa.or.jp/denkishiryo-bekkan/api/presentations/iiif/2/canvas/1586",
    "category": {
        "lvl0": "DKB02 渋沢栄一伝記資料. 別巻第2 日記 (大正4年-昭和5年), 集会日時通知表",
        "lvl1": "DKB02 渋沢栄一伝記資料. 別巻第2 日記 (大正4年-昭和5年), 集会日時通知表 > DKB20030m 昭和三年 1928"
    },
    "category_lvl0": "DKB02 渋沢栄一伝記資料. 別巻第2 日記 (大正4年-昭和5年), 集会日時通知表",
    "category_lvl1": "DKB20030m 昭和三年 1928",
    "date": {
        "lvl0": "1928",
        "lvl1": "1928 > 1928-10",
        "lvl2": "1928 > 1928-10 > 1928-10-04"
    },
    "date_lvl0": "1928",
    "date_lvl1": "1928-10",
    "date_lvl2": "1928-10-04",
    "description": "\n\n 四日  （木） \n\n\n午前八時半安藤義喬氏来約《（安東義喬）》（飛鳥山）\n\n\n午前十時半御出勤\n\n\n午前十一時末延道成氏来約（事ム所）\n\n\n午後六時入沢、大滝、林三先生来訪（飛鳥山）\n\n\n",
    "fullname": [
        "安藤義喬",
        "安東義喬"
    ],
    "label": "四日  （木）",
    "manifest": "https://eiichi.shibusawa.or.jp/denkishiryo-bekkan/api/presentations/iiif/2/manifest",
    "next": "DKB20030m-214",
    "objectID": "DKB20030m-213",
    "prev": "DKB20030m-212",
    "sort": "DKB20030m-0213",
    "source": "https://shibusawa-dlab.github.io/lab1/tei/DKB02.xml",
    "spatial": [
        "飛鳥山公園"
    ],
    "spatial_uri": [
        "https://shibusawa-dlab.github.io/lab1/api/place/飛鳥山公園"
    ],
    "temporal": "1928-10-04",
    "time": {
        "08:30:00": "<div><time when=\"08:30:00\">午前八時半</time><persName><surname>安藤</surname><forename>義喬</forename></persName>氏来約《（<persName><surname>安東</surname><forename>義喬</forename></persName>）》（<placeName corresp=\"#飛鳥山\">飛鳥山</placeName>）</div>"
    },
    "type": "day",
    "xml": "<div type=\"day\" xml:id=\"DKB20030m-213\">\n<head>\n<date when=\"1928-10-04\"> 四日 </date> （木） </head>\n<listEvent>\n<event>\n<p><time when=\"08:30:00\">午前八時半</time><persName><surname>安藤</surname><forename>義喬</forename></persName>氏来約《（<persName><surname>安東</surname><forename>義喬</forename></persName>）》（<placeName corresp=\"#飛鳥山\">飛鳥山</placeName>）</p>\n</event>\n<event>\n<p><time when=\"10:30:00\">午前十時半</time>御出勤</p>\n</event>\n<event>\n<p><time when=\"11:00:00\">午前十一時</time>末延道成氏来約（事ム所）</p>\n</event>\n<event>\n<p><time when=\"18:00:00\">午後六時</time><persName><surname>入沢</surname></persName>、大滝、林三先生来訪（<placeName corresp=\"#飛鳥山\">飛鳥山</placeName>）</p>\n</event>\n</listEvent>\n</div>",
    "year": "1928",
    "yearAndMonth": "1928-10"
}