{
    "agential": [],
    "agential_uri": [],
    "canvas": "https://eiichi.shibusawa.or.jp/denkishiryo-bekkan/api/presentations/iiif/2/canvas/1594",
    "category": {
        "lvl0": "DKB02 渋沢栄一伝記資料. 別巻第2 日記 (大正4年-昭和5年), 集会日時通知表",
        "lvl1": "DKB02 渋沢栄一伝記資料. 別巻第2 日記 (大正4年-昭和5年), 集会日時通知表 > DKB20031m 昭和四年 1929"
    },
    "category_lvl0": "DKB02 渋沢栄一伝記資料. 別巻第2 日記 (大正4年-昭和5年), 集会日時通知表",
    "category_lvl1": "DKB20031m 昭和四年 1929",
    "date": {
        "lvl0": "1929",
        "lvl1": "1929 > 1929-05",
        "lvl2": "1929 > 1929-05 > 1929-05-24"
    },
    "date_lvl0": "1929",
    "date_lvl1": "1929-05",
    "date_lvl2": "1929-05-24",
    "description": "\n\n 廿四日  （金） \n\n\n午後一・十分　事務所ニ御出勤\n\n\n",
    "fullname": [],
    "label": "廿四日  （金）",
    "manifest": "https://eiichi.shibusawa.or.jp/denkishiryo-bekkan/api/presentations/iiif/2/manifest",
    "next": "DKB20031m-68",
    "objectID": "DKB20031m-67",
    "prev": "DKB20031m-65",
    "sort": "DKB20031m-0067",
    "source": "https://shibusawa-dlab.github.io/lab1/tei/DKB02.xml",
    "spatial": [],
    "spatial_uri": [],
    "temporal": "1929-05-24",
    "time": {
        "13:10:00": "<div><time when=\"13:10:00\">午後一・十分</time>　事務所ニ御出勤</div>"
    },
    "type": "day",
    "xml": "<div type=\"day\" xml:id=\"DKB20031m-67\">\n<head>\n<date when=\"1929-05-24\"> 廿四日 </date> （金） </head>\n<listEvent>\n<event>\n<p><time when=\"13:10:00\">午後一・十分</time>　事務所ニ御出勤</p>\n</event>\n</listEvent>\n</div>",
    "year": "1929",
    "yearAndMonth": "1929-05"
}